openreview_downloader/__init__.py
openreview_downloader/cli.py
openreview_downloader-0.1.4.dist-info/METADATA
openreview_downloader-0.1.4.dist-info/WHEEL
openreview_downloader-0.1.4.dist-info/entry_points.txt
openreview_downloader-0.1.4.dist-info/licenses/LICENSE
openreview_downloader-0.1.4.dist-info/RECORD
