Metadata-Version: 2.4
Name: openreview_downloader
Version: 0.1.4
Summary: Download OpenReview papers by decision.
Project-URL: Homepage, https://github.com/mireklzicar/openreview_downloader
Project-URL: Repository, https://github.com/mireklzicar/openreview_downloader
Project-URL: Issues, https://github.com/mireklzicar/openreview_downloader/issues
Author-email: Miroslav Lzicar <lzicar2000@gmail.com>
License: Apache-2.0
License-File: LICENSE
Keywords: automation,downloader,iclr,icml,neurips,openreview,papers,scraping
Classifier: Development Status :: 3 - Alpha
Classifier: Intended Audience :: Developers
Classifier: Intended Audience :: Science/Research
Classifier: License :: OSI Approved :: Apache Software License
Classifier: Programming Language :: Python :: 3.9
Classifier: Programming Language :: Python :: 3.10
Classifier: Programming Language :: Python :: 3.11
Classifier: Programming Language :: Python :: 3.12
Classifier: Topic :: Scientific/Engineering :: Artificial Intelligence
Requires-Python: >=3.9
Requires-Dist: openreview-py<2.0.0,>=1.54.2
Requires-Dist: tqdm<5.0.0,>=4.67.0
Provides-Extra: dev
Requires-Dist: bump2version; extra == 'dev'
